uselessmodule.py
uselessmodule-1.0.9.dist-info/METADATA
uselessmodule-1.0.9.dist-info/WHEEL
uselessmodule-1.0.9.dist-info/top_level.txt
uselessmodule-1.0.9.dist-info/RECORD
