Metadata-Version: 2.1
Name: uselessmodule
Version: 1.0.9
Summary: Don't use this module, it's useless.
Home-page: UNKNOWN
Author: koreann
Author-email: pgw9486@kakao.com
License: UNKNOWN
Platform: UNKNOWN
